stot/__init__.py
stot/__main__.py
stot/ffexec.py
stot-0.0.2.dist-info/LICENSE
stot-0.0.2.dist-info/METADATA
stot-0.0.2.dist-info/WHEEL
stot-0.0.2.dist-info/entry_points.txt
stot-0.0.2.dist-info/top_level.txt
stot-0.0.2.dist-info/RECORD
