Metadata-Version: 2.1
Name: stot
Version: 0.0.2
Summary: real-time transcription of speech to text using whisper
Home-page: https://github.com/dsymbol/stot
Author: dsymbol
License: UNKNOWN
Platform: UNKNOWN
License-File: LICENSE
Requires-Dist: pyaudio
Requires-Dist: SpeechRecognition
Requires-Dist: requests
Requires-Dist: tqdm
Requires-Dist: torch
Requires-Dist: torchvision
Requires-Dist: torchaudio
Requires-Dist: openai-whisper
